message_pusher_sdk/__init__.py
message_pusher_sdk/message_pusher_sdk.py
message_pusher_sdk/tests/__init__.py
message_pusher_sdk/tests/config.json.example
message_pusher_sdk/tests/conftest.py
message_pusher_sdk/tests/test_utils.py
message_pusher_sdk-0.1.0.dist-info/LICENSE.md
message_pusher_sdk-0.1.0.dist-info/METADATA
message_pusher_sdk-0.1.0.dist-info/WHEEL
message_pusher_sdk-0.1.0.dist-info/entry_points.txt
message_pusher_sdk-0.1.0.dist-info/RECORD
