Metadata-Version: 2.1
Name: message-pusher-sdk
Version: 0.1.0
Summary: Python SDK for message-pusher
Home-page: https://pypi.org/project/message-pusher-sdk
License: MIT
Author: 117503445
Author-email: t117503445@gmail.com
Requires-Python: >=3.10,<4.0
Classifier: Development Status :: 1 - Planning
Classifier: License :: OSI Approved :: MIT License
Classifier: Natural Language :: English
Classifier: Operating System :: OS Independent
Classifier: Programming Language :: Python
Classifier: Programming Language :: Python :: 3
Classifier: Programming Language :: Python :: 3.10
Classifier: Programming Language :: Python :: 3.11
Classifier: Programming Language :: Python :: 3
Classifier: Programming Language :: Python :: 3.10
Requires-Dist: click
Requires-Dist: minilog
Requires-Dist: types-requests (>=2.28.11.17,<3.0.0.0)
Project-URL: Documentation, https://message-pusher-sdk.readthedocs.io
Project-URL: Repository, https://github.com/117503445/message-pusher-python-sdk
